setup.py
StartingVerbExtractor/__init__.py
StartingVerbExtractor.egg-info/PKG-INFO
StartingVerbExtractor.egg-info/SOURCES.txt
StartingVerbExtractor.egg-info/dependency_links.txt
StartingVerbExtractor.egg-info/not-zip-safe
StartingVerbExtractor.egg-info/top_level.txt