Metadata-Version: 2.1
Name: StartingVerbExtractor
Version: 1.3
Summary: StartingVerbExtractor package
Author: Felipe Rainel
Author-email: raineldias88@gmail.com
